.gitignore
README.rst
bootstrap.py
buildout.cfg
setup.py
docs/HISTORY.txt
src/dj/__init__.py
src/dj.paste.egg-info/PKG-INFO
src/dj.paste.egg-info/SOURCES.txt
src/dj.paste.egg-info/dependency_links.txt
src/dj.paste.egg-info/entry_points.txt
src/dj.paste.egg-info/namespace_packages.txt
src/dj.paste.egg-info/not-zip-safe
src/dj.paste.egg-info/requires.txt
src/dj.paste.egg-info/top_level.txt
src/dj/paste/README.txt
src/dj/paste/__init__.py
src/dj/paste/paste.py
src/dj/paste/tests/__init__.py
src/dj/paste/tests/development.ini
src/dj/paste/tests/test_django.py
src/dj/paste/tests/django/__init__.py
src/dj/paste/tests/django/manage.py
src/dj/paste/tests/django/settings.py
src/dj/paste/tests/django/urls.py
src/dj/paste/tests/django/wrappers.py