Metadata-Version: 1.0
Name: dj.paste
Version: 1.14
Summary: Yet another WSGI Paste factory for paste sponsored by Makina Corpus
Home-page: https://github.com/kiorky/dj.paste
Author: Mathieu Pasquet
Author-email: kiorky@cryptelium.net
License: BSD
Platform: UNKNOWN
Classifier: Programming Language :: Python
Classifier: Topic :: Software Development :: Libraries :: Python Modules
